{
  "buttons": [
    {
      "action": "ua",
      "textKey": "Українська",
      "width": 150,
      "height": 150,
      "x": 1800,
      "y": 150,
      "fontScale": 2.0,
      "stage": "settingsStage"
    },
    {
      "action": "en",
      "textKey": "English",
      "width": 150,
      "height": 150,
      "x": 1800,
      "y": 150,
      "fontScale": 2.0,
      "stage": "settingsStage"
    },
    {
      "action": "de",
      "textKey": "Deustch",
      "width": 150,
      "height": 150,
      "x": 1800,
      "y": 150,
      "fontScale": 2.0,
      "stage": "settingsStage"
    },
}
